fast_flights/__init__.py
fast_flights/fetcher.py
fast_flights/model.py
fast_flights/parser.py
fast_flights/py.typed
fast_flights/querying.py
fast_flights/types.py
fast_flights/integrations/__init__.py
fast_flights/integrations/base.py
fast_flights/integrations/bright_data.py
fast_flights/pb/__init__.py
fast_flights/pb/flights.proto
fast_flights/pb/flights_pb2.py
fast_flights/pb/flights_pb2.pyi
fast_flights-3.0rc0.dist-info/licenses/LICENSE
fast_flights-3.0rc0.dist-info/WHEEL
fast_flights-3.0rc0.dist-info/METADATA
fast_flights-3.0rc0.dist-info/RECORD
