Metadata-Version: 2.4
Name: fast-flights
Version: 3.0rc0
Summary: The fast, robust, strongly-typed Google Flights scraper (API) implemented in Python.
Keywords: flights,google,google-flights,scraper,protobuf,travel,trip,passengers,airport
Author-email: AWeirdDev <aweirdscratcher@gmail.com>
Requires-Python: >=3.10
Classifier: Programming Language :: Python :: 3
Classifier: License :: OSI Approved :: MIT License
Classifier: Operating System :: OS Independent
License-File: LICENSE
Requires-Dist: primp
Requires-Dist: protobuf>=5.27.0
Requires-Dist: selectolax
Requires-Dist: rjsonc
Requires-Dist: playwright ; extra == "local"
Project-URL: Documentation, https://aweirddev.github.io/flights/
Project-URL: Issues, https://github.com/AWeirdDev/flights/issues
Project-URL: Source, https://github.com/AWeirdDev/flights
Provides-Extra: local
